palm_kernel/__init__.py
palm_kernel/palm_kernel.py
palm_kernel-0.0.2.dist-info/LICENSE
palm_kernel-0.0.2.dist-info/METADATA
palm_kernel-0.0.2.dist-info/WHEEL
palm_kernel-0.0.2.dist-info/top_level.txt
palm_kernel-0.0.2.dist-info/RECORD
