Metadata-Version: 2.1
Name: palm-kernel
Version: 0.0.2
Summary: A python package for geostatistical analysis
Home-page: https://github.com/edudzikorku/palm-kernel
Author: Edudzi Akpakli
Author-email: kedudzi007@gmail.com
License: MIT license
Keywords: palm_kernel
Classifier: Development Status :: 2 - Pre-Alpha
Classifier: Intended Audience :: Developers
Classifier: License :: OSI Approved :: MIT License
Classifier: Natural Language :: English
Classifier: Programming Language :: Python :: 3
Classifier: Programming Language :: Python :: 3.7
Classifier: Programming Language :: Python :: 3.8
Classifier: Programming Language :: Python :: 3.9
Classifier: Programming Language :: Python :: 3.10
Requires-Python: >=3.7
License-File: LICENSE
